activations/LeakyReLU.py
activations/Linear.py
activations/ReLU.py
activations/Sigmoid.py
activations/Softmax.py
activations/TanH.py
activations/__init__.py
datasets/__init__.py
initializers/__init__.py
initializers/weight.py
layers/__init__.py
layers/convolution.py
layers/dense_layer.py
layers/dropout.py
layers/flatten.py
layers/input.py
layers/reshape.py
losses/__init__.py
losses/crossentropy.py
losses/error.py
optimizers/__init__.py
optimizers/adagrad.py
optimizers/adam.py
optimizers/rmsprop.py
optimizers/sgd.py
preprocessing/__init__.py
saving/__init__.py
saving/loading.py
saving/saving.py
utils/__init__.py
utils/image.py
deepend-0.0.2.dist-info/LICENSE
deepend-0.0.2.dist-info/METADATA
deepend-0.0.2.dist-info/WHEEL
deepend-0.0.2.dist-info/top_level.txt
deepend-0.0.2.dist-info/RECORD
