Metadata-Version: 2.1
Name: deepend
Version: 0.0.2
Summary: Advanced end-to-end machine learning framework.
Home-page: https://github.com/Letsmoe/deepend
Author: Moritz Utcke
Author-email: moritz.utcke@gmx.de
License: UNKNOWN
Project-URL: Bug Tracker, https://github.com/Letsmoe/deepend/issues
Platform: UNKNOWN
Classifier: Programming Language :: Python :: 3
Classifier: License :: OSI Approved :: MIT License
Classifier: Operating System :: OS Independent
Requires-Python: >=3.6
License-File: LICENSE
Requires-Dist: sys
Requires-Dist: os
Requires-Dist: numpy
Requires-Dist: matplotlib
Requires-Dist: cv2
Requires-Dist: datetime
Requires-Dist: h5py
